senlerpy/__init__.py
senlerpy/exceptions.py
senlerpy/methods.py
senlerpy/request.py
senlerpy/senler.py
senlerpy-2.2.1.dist-info/LICENSE
senlerpy-2.2.1.dist-info/METADATA
senlerpy-2.2.1.dist-info/WHEEL
senlerpy-2.2.1.dist-info/top_level.txt
senlerpy-2.2.1.dist-info/RECORD
