Metadata-Version: 2.1
Name: senlerpy
Version: 2.2.1
Summary: Wrapper for senler.ru API
Home-page: https://github.com/tezmen/SenlerPy
Author: tezmen
Author-email: tezmenpro@gmail.com
License: Apache License, Version 2.0, see LICENSE file
Download-URL: https://github.com/tezmen/SenlerPy/archive/master.zip
Keywords: senler,api,wrapper
Platform: UNKNOWN
Classifier: License :: OSI Approved :: Apache Software License
Classifier: Operating System :: OS Independent
Classifier: Environment :: Console
Classifier: Development Status :: 3 - Alpha
Classifier: Programming Language :: Python
Classifier: Programming Language :: Python :: 3.7
Classifier: Programming Language :: Python :: Implementation :: PyPy
Requires-Dist: chardet (==3.0.4)
Requires-Dist: idna (==2.8)
Requires-Dist: requests (==2.21.0)
Requires-Dist: urllib3 (==1.24.1)
